djangocms_zb_organizations/__init__.py
djangocms_zb_organizations/admin.py
djangocms_zb_organizations/apps.py
djangocms_zb_organizations/cms_plugins.py
djangocms_zb_organizations/urls.py
djangocms_zb_organizations/views.py
djangocms_zb_organizations/lib/__init__.py
djangocms_zb_organizations/lib/choices.py
djangocms_zb_organizations/lib/exceptions/__init__.py
djangocms_zb_organizations/lib/exceptions/data_required.py
djangocms_zb_organizations/lib/exceptions/not_found.py
djangocms_zb_organizations/lib/helpers/__init__.py
djangocms_zb_organizations/lib/helpers/extra_multiple_file_field.py
djangocms_zb_organizations/lib/managers/__init__.py
djangocms_zb_organizations/lib/managers/geo_organization.py
djangocms_zb_organizations/lib/managers/organization.py
djangocms_zb_organizations/lib/serializers/__init__.py
djangocms_zb_organizations/lib/serializers/geo_organization.py
djangocms_zb_organizations/lib/serializers/organization.py
djangocms_zb_organizations/lib/services/__init__.py
djangocms_zb_organizations/lib/services/geo_organization.py
djangocms_zb_organizations/lib/services/organization.py
djangocms_zb_organizations/locale/es/LC_MESSAGES/django.mo
djangocms_zb_organizations/locale/es/LC_MESSAGES/django.po
djangocms_zb_organizations/migrations/0001_initial.py
djangocms_zb_organizations/migrations/0002_alter_microsite_slug.py
djangocms_zb_organizations/migrations/0003_auto_20220601_1128.py
djangocms_zb_organizations/migrations/0004_alter_microsite_slug.py
djangocms_zb_organizations/migrations/0005_alter_microsite_slug.py
djangocms_zb_organizations/migrations/0006_alter_microsite_slug.py
djangocms_zb_organizations/migrations/0007_auto_20220601_1511.py
djangocms_zb_organizations/migrations/0008_alter_orgpicture_picture.py
djangocms_zb_organizations/migrations/0009_auto_20220601_1658.py
djangocms_zb_organizations/migrations/0010_rename_image_catalog_picture.py
djangocms_zb_organizations/migrations/0011_alter_microsite_content.py
djangocms_zb_organizations-2.1.5.dist-info/licenses/LICENSE
djangocms_zb_organizations-2.1.5.dist-info/METADATA
djangocms_zb_organizations-2.1.5.dist-info/WHEEL
djangocms_zb_organizations-2.1.5.dist-info/top_level.txt
djangocms_zb_organizations-2.1.5.dist-info/RECORD
