Metadata-Version: 2.4
Name: djangocms-zb-organizations
Version: 2.1.5
Summary: Zibanu Organizations Plugin for Django CMS
Author-email: Jhony Gonzalez <jhonny.gonzalez@cqinversiones.co>
License-Expression: GPL-3.0-or-later
Keywords: django,zibanu,organizations,openstreetmap
Classifier: Programming Language :: Python :: 3.9
Classifier: Programming Language :: Python :: 3.10
Classifier: Programming Language :: Python :: 3.11
Classifier: Development Status :: 5 - Production/Stable
Classifier: Framework :: Django
Classifier: Framework :: Django :: 3.2
Classifier: Framework :: Django :: 4
Classifier: Framework :: Django :: 5
Classifier: Environment :: Web Environment
Classifier: Operating System :: OS Independent
Classifier: Topic :: Internet :: WWW/HTTP
Requires-Python: >=3.7
License-File: LICENSE
Requires-Dist: Django~=3.2
Requires-Dist: django-cms>=3.9
Requires-Dist: django-filer
Requires-Dist: django-ckeditor
Requires-Dist: django-cities-light
Requires-Dist: geopandas
Requires-Dist: gdal>=3.0.4
Requires-Dist: djangorestframework-gis
Dynamic: license-file
